{"get": "fixtures", "parameters": {"id": "204257"}, "errors": [], "results": 1, "paging": {"current": 1, "total": 1}, "response": [{"fixture": {"id": 204257, "referee": null, "timezone": "UTC", "date": "2013-12-20T19:30:00+00:00", "timestamp": 1387567800, "periods": {"first": 1387567800, "second": 1387571400}, "venue": {"id": null, "name": "Estadio Manuel Martínez Valero (Elche)", "city": null}, "status": {"long": "Match Finished", "short": "FT", "elapsed": 90}}, "league": {"id": 140, "name": "La Liga", "country": "Spain", "logo": "https://media-3.api-sports.io/football/leagues/140.png", "flag": "https://media-1.api-sports.io/flags/es.svg", "season": 2013, "round": "Regular Season - 17"}, "teams": {"home": {"id": 797, "name": "Elche", "logo": "https://media-3.api-sports.io/football/teams/797.png", "winner": false}, "away": {"id": 535, "name": "Malaga", "logo": "https://media-1.api-sports.io/football/teams/535.png", "winner": true}}, "goals": {"home": 0, "away": 1}, "score": {"halftime": {"home": 0, "away": 1}, "fulltime": {"home": 0, "away": 1}, "extratime": {"home": null, "away": null}, "penalty": {"home": null, "away": null}}, "events": [{"time": {"elapsed": 6, "extra": null}, "team": {"id": 535, "name": "Malaga", "logo": "https://media-1.api-sports.io/football/teams/535.png"}, "player": {"id": 25409, "name": "Ignacio Camacho"}, "assist": {"id": 104838, "name": "Duda"}, "type": "Goal", "detail": "Normal Goal", "comments": null}, {"time": {"elapsed": 55, "extra": null}, "team": {"id": 535, "name": "Malaga", "logo": "https://media-2.api-sports.io/football/teams/535.png"}, "player": {"id": 12088, "name": "P. Morales"}, "assist": {"id": 104624, "name": "Samu"}, "type": "subst", "detail": "Substitution 1", "comments": null}, {"time": {"elapsed": 65, "extra": null}, "team": {"id": 797, "name": "Elche", "logo": "https://media-2.api-sports.io/football/teams/797.png"}, "player": {"id": 47002, "name": "Fidel"}, "assist": {"id": 105093, "name": "Mantecón"}, "type": "subst", "detail": "Substitution 1", "comments": null}, {"time": {"elapsed": 73, "extra": null}, "team": {"id": 797, "name": "Elche", "logo": "https://media-3.api-sports.io/football/teams/797.png"}, "player": {"id": 363, "name": "R. Boakye"}, "assist": {"id": 47180, "name": "Cristian Herrera"}, "type": "subst", "detail": "Substitution 2", "comments": null}, {"time": {"elapsed": 79, "extra": null}, "team": {"id": 535, "name": "Malaga", "logo": "https://media-1.api-sports.io/football/teams/535.png"}, "player": {"id": 47262, "name": "Portillo"}, "assist": {"id": 51564, "name": "M. Angeleri"}, "type": "subst", "detail": "Substitution 2", "comments": null}, {"time": {"elapsed": 81, "extra": null}, "team": {"id": 797, "name": "Elche", "logo": "https://media-3.api-sports.io/football/teams/797.png"}, "player": {"id": 47415, "name": "Rubén Pérez"}, "assist": {"id": 92252, "name": "Aaron Níguez"}, "type": "subst", "detail": "Substitution 3", "comments": null}, {"time": {"elapsed": 90, "extra": 3}, "team": {"id": 535, "name": "Malaga", "logo": "https://media-1.api-sports.io/football/teams/535.png"}, "player": {"id": 104838, "name": "Duda"}, "assist": {"id": 70775, "name": "R. Santa Cruz"}, "type": "subst", "detail": "Substitution 3", "comments": null}], "lineups": [{"team": {"id": 797, "name": "Elche", "logo": "https://media-1.api-sports.io/football/teams/797.png", "colors": null}, "startXI": [{"player": {"id": 105111, "name": "Toño", "number": 13, "pos": null, "grid": null}}, {"player": {"id": 47257, "name": "D. Suárez", "number": 2, "pos": null, "grid": null}}, {"player": {"id": 105071, "name": "Edu Albácar", "number": 21, "pos": null, "grid": null}}, {"player": {"id": 116849, "name": "Sergio Pelegrín", "number": 18, "pos": null, "grid": null}}, {"player": {"id": 44333, "name": "Botía", "number": 3, "pos": null, "grid": null}}, {"player": {"id": 18827, "name": "C. Sánchez", "number": 24, "pos": null, "grid": null}}, {"player": {"id": 47415, "name": "Rubén Pérez", "number": 6, "pos": null, "grid": null}}, {"player": {"id": 47002, "name": "Fidel", "number": 16, "pos": null, "grid": null}}, {"player": {"id": 59963, "name": "Coro", "number": 25, "pos": null, "grid": null}}, {"player": {"id": 363, "name": "R. Boakye", "number": 9, "pos": null, "grid": null}}, {"player": {"id": 51012, "name": "Carles Gil", "number": 15, "pos": null, "grid": null}}], "substitutes": [{"player": {"id": 105093, "name": "Mantecón", "number": 8, "pos": null, "grid": null}}, {"player": {"id": 47180, "name": "Cristian Herrera", "number": 31, "pos": null, "grid": null}}, {"player": {"id": 92252, "name": "Aaron Níguez", "number": 7, "pos": null, "grid": null}}, {"player": {"id": 104844, "name": "Manu Herrera", "number": 1, "pos": null, "grid": null}}, {"player": {"id": 116881, "name": "Rivera", "number": 5, "pos": null, "grid": null}}, {"player": {"id": 47230, "name": "Javi Márquez", "number": 17, "pos": null, "grid": null}}, {"player": {"id": 105080, "name": "Cisma", "number": 23, "pos": null, "grid": null}}], "coach": {"id": null, "name": null}, "formation": null}, {"team": {"id": 535, "name": "Malaga", "logo": "https://media-2.api-sports.io/football/teams/535.png", "colors": null}, "startXI": [{"player": {"id": 2275, "name": "W. Caballero", "number": 13, "pos": null, "grid": null}}, {"player": {"id": 104863, "name": "Weligton", "number": 3, "pos": null, "grid": null}}, {"player": {"id": 47255, "name": "Antunes", "number": 5, "pos": null, "grid": null}}, {"player": {"id": 46767, "name": "Sergio Sánchez", "number": 21, "pos": null, "grid": null}}, {"player": {"id": 83132, "name": "Jesús Gámez", "number": 2, "pos": null, "grid": null}}, {"player": {"id": 41475, "name": "F. Tissone", "number": 12, "pos": null, "grid": null}}, {"player": {"id": 104838, "name": "Duda", "number": 17, "pos": null, "grid": null}}, {"player": {"id": 25409, "name": "Ignacio Camacho", "number": 6, "pos": null, "grid": null}}, {"player": {"id": 12088, "name": "P. Morales", "number": 14, "pos": null, "grid": null}}, {"player": {"id": 47320, "name": "Juanmi", "number": 26, "pos": null, "grid": null}}, {"player": {"id": 47262, "name": "Portillo", "number": 8, "pos": null, "grid": null}}], "substitutes": [{"player": {"id": 104624, "name": "Samu", "number": 24, "pos": null, "grid": null}}, {"player": {"id": 51564, "name": "M. Angeleri", "number": 15, "pos": null, "grid": null}}, {"player": {"id": 70775, "name": "R. Santa Cruz", "number": 9, "pos": null, "grid": null}}, {"player": {"id": 1335, "name": "C. Kameni", "number": 1, "pos": null, "grid": null}}, {"player": {"id": 116597, "name": "Flávio", "number": 4, "pos": null, "grid": null}}, {"player": {"id": 114180, "name": "B. Anderson", "number": 10, "pos": null, "grid": null}}, {"player": {"id": 47336, "name": "Sergi Darder", "number": 30, "pos": null, "grid": null}}], "coach": {"id": null, "name": null}, "formation": null}], "statistics": [], "players": []}]}