{"get": "fixtures", "parameters": {"id": "204230"}, "errors": [], "results": 1, "paging": {"current": 1, "total": 1}, "response": [{"fixture": {"id": 204230, "referee": null, "timezone": "UTC", "date": "2013-11-23T19:00:00+00:00", "timestamp": 1385233200, "periods": {"first": 1385233200, "second": 1385236800}, "venue": {"id": null, "name": "Estadio de los Juegos Mediterr\u00e1neos (Almer\u00eda)", "city": null}, "status": {"long": "Match Finished", "short": "FT", "elapsed": 90}}, "league": {"id": 140, "name": "La Liga", "country": "Spain", "logo": "https://media-3.api-sports.io/football/leagues/140.png", "flag": "https://media-3.api-sports.io/flags/es.svg", "season": 2013, "round": "Regular Season - 14"}, "teams": {"home": {"id": 723, "name": "Almeria", "logo": "https://media-3.api-sports.io/football/teams/723.png", "winner": false}, "away": {"id": 541, "name": "Real Madrid", "logo": "https://media-2.api-sports.io/football/teams/541.png", "winner": true}}, "goals": {"home": 0, "away": 5}, "score": {"halftime": {"home": 0, "away": 1}, "fulltime": {"home": 0, "away": 5}, "extratime": {"home": null, "away": null}, "penalty": {"home": null, "away": null}}, "events": [{"time": {"elapsed": 3, "extra": null}, "team": {"id": 541, "name": "Real Madrid", "logo": "https://media-3.api-sports.io/football/teams/541.png"}, "player": {"id": 874, "name": "Cristiano Ronaldo"}, "assist": {"id": 745, "name": "Isco"}, "type": "Goal", "detail": "Normal Goal", "comments": null}, {"time": {"elapsed": 54, "extra": null}, "team": {"id": 541, "name": "Real Madrid", "logo": "https://media-2.api-sports.io/football/teams/541.png"}, "player": {"id": 874, "name": "Cristiano Ronaldo"}, "assist": {"id": 1585, "name": "Jes\u00e9 Rodr\u00edguez"}, "type": "subst", "detail": "Substitution 1", "comments": null}, {"time": {"elapsed": 59, "extra": null}, "team": {"id": 723, "name": "Almeria", "logo": "https://media-1.api-sports.io/football/teams/723.png"}, "player": {"id": 47108, "name": "Verza"}, "assist": {"id": 116841, "name": "Soriano"}, "type": "subst", "detail": "Substitution 1", "comments": null}, {"time": {"elapsed": 61, "extra": null}, "team": {"id": 541, "name": "Real Madrid", "logo": "https://media-1.api-sports.io/football/teams/541.png"}, "player": {"id": 759, "name": "K. Benzema"}, "assist": {"id": 1585, "name": "Jes\u00e9 Rodr\u00edguez"}, "type": "Goal", "detail": "Normal Goal", "comments": null}, {"time": {"elapsed": 62, "extra": null}, "team": {"id": 541, "name": "Real Madrid", "logo": "https://media-3.api-sports.io/football/teams/541.png"}, "player": {"id": 759, "name": "K. Benzema"}, "assist": {"id": 59, "name": "\u00c1lvaro Morata"}, "type": "subst", "detail": "Substitution 2", "comments": null}, {"time": {"elapsed": 66, "extra": null}, "team": {"id": 723, "name": "Almeria", "logo": "https://media-3.api-sports.io/football/teams/723.png"}, "player": {"id": 16467, "name": "H. Pellerano"}, "assist": {"id": 60111, "name": "Marcos T\u00e9bar"}, "type": "subst", "detail": "Substitution 2", "comments": null}, {"time": {"elapsed": 72, "extra": null}, "team": {"id": 541, "name": "Real Madrid", "logo": "https://media-2.api-sports.io/football/teams/541.png"}, "player": {"id": 758, "name": "G. Bale"}, "assist": {"id": null, "name": null}, "type": "Goal", "detail": "Normal Goal", "comments": null}, {"time": {"elapsed": 73, "extra": null}, "team": {"id": 723, "name": "Almeria", "logo": "https://media-1.api-sports.io/football/teams/723.png"}, "player": {"id": 2047, "name": "Aleix Vidal"}, "assist": {"id": 105065, "name": "\u00d3scar D\u00edaz"}, "type": "subst", "detail": "Substitution 3", "comments": null}, {"time": {"elapsed": 73, "extra": null}, "team": {"id": 541, "name": "Real Madrid", "logo": "https://media-2.api-sports.io/football/teams/541.png"}, "player": {"id": 47310, "name": "Illarramendi"}, "assist": {"id": 747, "name": "Casemiro"}, "type": "subst", "detail": "Substitution 3", "comments": null}, {"time": {"elapsed": 75, "extra": null}, "team": {"id": 541, "name": "Real Madrid", "logo": "https://media-1.api-sports.io/football/teams/541.png"}, "player": {"id": 745, "name": "Isco"}, "assist": {"id": 1585, "name": "Jes\u00e9 Rodr\u00edguez"}, "type": "Goal", "detail": "Normal Goal", "comments": null}, {"time": {"elapsed": 81, "extra": null}, "team": {"id": 541, "name": "Real Madrid", "logo": "https://media-2.api-sports.io/football/teams/541.png"}, "player": {"id": 59, "name": "\u00c1lvaro Morata"}, "assist": {"id": 747, "name": "Casemiro"}, "type": "Goal", "detail": "Normal Goal", "comments": null}], "lineups": [{"team": {"id": 723, "name": "Almeria", "logo": "https://media-1.api-sports.io/football/teams/723.png", "colors": null}, "startXI": [{"player": {"id": 105019, "name": "Esteban", "number": 1, "pos": null, "grid": null}}, {"player": {"id": 105003, "name": "N\u00e9lson", "number": 22, "pos": null, "grid": null}}, {"player": {"id": 46788, "name": "S. Dubarbier", "number": 16, "pos": null, "grid": null}}, {"player": {"id": 6207, "name": "M. Torsiglieri", "number": 2, "pos": null, "grid": null}}, {"player": {"id": 16467, "name": "H. Pellerano", "number": 4, "pos": null, "grid": null}}, {"player": {"id": 46915, "name": "\u00c1ngel Trujillo", "number": 5, "pos": null, "grid": null}}, {"player": {"id": 47108, "name": "Verza", "number": 7, "pos": null, "grid": null}}, {"player": {"id": 46685, "name": "R. Azeez", "number": 12, "pos": null, "grid": null}}, {"player": {"id": 2047, "name": "Aleix Vidal", "number": 8, "pos": null, "grid": null}}, {"player": {"id": 1650, "name": "Suso", "number": 17, "pos": null, "grid": null}}, {"player": {"id": 46696, "name": "Rodri", "number": 10, "pos": null, "grid": null}}], "substitutes": [{"player": {"id": 116841, "name": "Soriano", "number": 23, "pos": null, "grid": null}}, {"player": {"id": 60111, "name": "Marcos T\u00e9bar", "number": 6, "pos": null, "grid": null}}, {"player": {"id": 105065, "name": "\u00d3scar D\u00edaz", "number": 9, "pos": null, "grid": null}}, {"player": {"id": 47506, "name": "Ra\u00fal Garc\u00eda", "number": 14, "pos": null, "grid": null}}, {"player": {"id": 116892, "name": "Rafita", "number": 20, "pos": null, "grid": null}}, {"player": {"id": 95571, "name": "O. Ustari", "number": 25, "pos": null, "grid": null}}, {"player": {"id": 2156, "name": "H\u00e9lder Barbosa", "number": 11, "pos": null, "grid": null}}], "coach": {"id": null, "name": null}, "formation": null}, {"team": {"id": 541, "name": "Real Madrid", "logo": "https://media-2.api-sports.io/football/teams/541.png", "colors": null}, "startXI": [{"player": {"id": 47327, "name": "Diego L\u00f3pez", "number": 25, "pos": null, "grid": null}}, {"player": {"id": 738, "name": "Sergio Ramos", "number": 4, "pos": null, "grid": null}}, {"player": {"id": 373, "name": "Pepe", "number": 3, "pos": null, "grid": null}}, {"player": {"id": 90521, "name": "Arbeloa", "number": 17, "pos": null, "grid": null}}, {"player": {"id": 733, "name": "Daniel Carvajal", "number": 15, "pos": null, "grid": null}}, {"player": {"id": 90657, "name": "Xabi Alonso", "number": 14, "pos": null, "grid": null}}, {"player": {"id": 758, "name": "G. Bale", "number": 11, "pos": null, "grid": null}}, {"player": {"id": 47310, "name": "Illarramendi", "number": 24, "pos": null, "grid": null}}, {"player": {"id": 745, "name": "Isco", "number": 23, "pos": null, "grid": null}}, {"player": {"id": 874, "name": "Cristiano Ronaldo", "number": 7, "pos": null, "grid": null}}, {"player": {"id": 759, "name": "K. Benzema", "number": 9, "pos": null, "grid": null}}], "substitutes": [{"player": {"id": 1585, "name": "Jes\u00e9 Rodr\u00edguez", "number": 20, "pos": null, "grid": null}}, {"player": {"id": 59, "name": "\u00c1lvaro Morata", "number": 21, "pos": null, "grid": null}}, {"player": {"id": 747, "name": "Casemiro", "number": 16, "pos": null, "grid": null}}, {"player": {"id": 367, "name": "Casillas", "number": 1, "pos": null, "grid": null}}, {"player": {"id": 735, "name": "Nacho", "number": 18, "pos": null, "grid": null}}, {"player": {"id": 754, "name": "L. Modri\u0107", "number": 19, "pos": null, "grid": null}}, {"player": {"id": 37019, "name": "Jos\u00e9 Rodr\u00edguez", "number": 26, "pos": null, "grid": null}}], "coach": {"id": null, "name": null}, "formation": null}], "statistics": [], "players": []}]}