{"get": "fixtures", "parameters": {"id": "214153"}, "errors": [], "results": 1, "paging": {"current": 1, "total": 1}, "response": [{"fixture": {"id": 214153, "referee": "Antonio Mateu", "timezone": "UTC", "date": "2019-11-24T15:00:00+00:00", "timestamp": 1574607600, "periods": {"first": 1574607600, "second": 1574611200}, "venue": {"id": 1472, "name": "Estadio Municipal de Ipur\u00faa", "city": "Eibar"}, "status": {"long": "Match Finished", "short": "FT", "elapsed": 90}}, "league": {"id": 140, "name": "La Liga", "country": "Spain", "logo": "https://media-1.api-sports.io/football/leagues/140.png", "flag": "https://media-2.api-sports.io/flags/es.svg", "season": 2019, "round": "Regular Season - 14"}, "teams": {"home": {"id": 545, "name": "Eibar", "logo": "https://media-2.api-sports.io/football/teams/545.png", "winner": false}, "away": {"id": 542, "name": "Alaves", "logo": "https://media-3.api-sports.io/football/teams/542.png", "winner": true}}, "goals": {"home": 0, "away": 2}, "score": {"halftime": {"home": 0, "away": 0}, "fulltime": {"home": 0, "away": 2}, "extratime": {"home": null, "away": null}, "penalty": {"home": null, "away": null}}, "events": [{"time": {"elapsed": 37, "extra": null}, "team": {"id": 542, "name": "Alaves", "logo": "https://media-3.api-sports.io/football/teams/542.png"}, "player": {"id": 47360, "name": "Ximo Navarro"}, "assist": {"id": null, "name": null}, "type": "Card", "detail": "Yellow Card", "comments": null}, {"time": {"elapsed": 65, "extra": null}, "team": {"id": 545, "name": "Eibar", "logo": "https://media-2.api-sports.io/football/teams/545.png"}, "player": {"id": 47395, "name": "Sergi Enrich"}, "assist": {"id": 47394, "name": "Charles"}, "type": "subst", "detail": "Substitution 1", "comments": null}, {"time": {"elapsed": 65, "extra": null}, "team": {"id": 542, "name": "Alaves", "logo": "https://media-3.api-sports.io/football/teams/542.png"}, "player": {"id": 133453, "name": "Borja Sainz"}, "assist": {"id": 47518, "name": "Pere Pons"}, "type": "subst", "detail": "Substitution 1", "comments": null}, {"time": {"elapsed": 73, "extra": null}, "team": {"id": 542, "name": "Alaves", "logo": "https://media-1.api-sports.io/football/teams/542.png"}, "player": {"id": 18833, "name": "Lucas P\u00e9rez"}, "assist": {"id": 18907, "name": "Joselu"}, "type": "subst", "detail": "Substitution 2", "comments": null}, {"time": {"elapsed": 80, "extra": null}, "team": {"id": 542, "name": "Alaves", "logo": "https://media-1.api-sports.io/football/teams/542.png"}, "player": {"id": 3426, "name": "Mubarak Wakaso"}, "assist": {"id": null, "name": null}, "type": "Card", "detail": "Yellow Card", "comments": null}, {"time": {"elapsed": 81, "extra": null}, "team": {"id": 545, "name": "Eibar", "logo": "https://media-1.api-sports.io/football/teams/545.png"}, "player": {"id": 47384, "name": "Cote"}, "assist": {"id": 47378, "name": "Bigas"}, "type": "subst", "detail": "Substitution 2", "comments": null}, {"time": {"elapsed": 85, "extra": null}, "team": {"id": 542, "name": "Alaves", "logo": "https://media-3.api-sports.io/football/teams/542.png"}, "player": {"id": 18907, "name": "Joselu"}, "assist": {"id": 2047, "name": "Aleix Vidal"}, "type": "Goal", "detail": "Normal Goal", "comments": null}, {"time": {"elapsed": 87, "extra": null}, "team": {"id": 545, "name": "Eibar", "logo": "https://media-2.api-sports.io/football/teams/545.png"}, "player": {"id": 47387, "name": "P. Diop"}, "assist": {"id": 47382, "name": "Ramis"}, "type": "subst", "detail": "Substitution 3", "comments": null}, {"time": {"elapsed": 88, "extra": null}, "team": {"id": 545, "name": "Eibar", "logo": "https://media-2.api-sports.io/football/teams/545.png"}, "player": {"id": 47377, "name": "Anaitz Arbilla"}, "assist": {"id": null, "name": null}, "type": "Card", "detail": "Yellow Card", "comments": null}, {"time": {"elapsed": 90, "extra": 2}, "team": {"id": 542, "name": "Alaves", "logo": "https://media-1.api-sports.io/football/teams/542.png"}, "player": {"id": 3426, "name": "M. Wakaso"}, "assist": {"id": 534, "name": "L. Magall\u00e1n"}, "type": "subst", "detail": "Substitution 3", "comments": null}, {"time": {"elapsed": 90, "extra": 1}, "team": {"id": 542, "name": "Alaves", "logo": "https://media-1.api-sports.io/football/teams/542.png"}, "player": {"id": 18907, "name": "Joselu"}, "assist": {"id": 47518, "name": "Pere Pons"}, "type": "Goal", "detail": "Normal Goal", "comments": null}], "lineups": [{"team": {"id": 545, "name": "Eibar", "logo": "https://media-1.api-sports.io/football/teams/545.png", "colors": null}, "coach": {"id": 1598, "name": "Mendilibar", "photo": "https://media-3.api-sports.io/football/coachs/1598.png"}, "formation": "4-4-2", "startXI": [{"player": {"id": 2813, "name": "Marko Dmitrovi\u0107", "number": 1, "pos": "G", "grid": "1:1"}}, {"player": {"id": 47386, "name": "Pablo De Blasis", "number": 16, "pos": "D", "grid": "2:4"}}, {"player": {"id": 47383, "name": "Paulo Oliveira", "number": 12, "pos": "D", "grid": "2:3"}}, {"player": {"id": 47377, "name": "Anaitz Arbilla", "number": 23, "pos": "D", "grid": "2:2"}}, {"player": {"id": 47384, "name": "Jos\u00e9 \u00c1ngel", "number": 15, "pos": "D", "grid": "2:1"}}, {"player": {"id": 47390, "name": "Fabi\u00e1n Orellana", "number": 14, "pos": "M", "grid": "3:4"}}, {"player": {"id": 47387, "name": "Papakouli Diop", "number": 8, "pos": "M", "grid": "3:3"}}, {"player": {"id": 47388, "name": "Gonzalo Escalante", "number": 5, "pos": "M", "grid": "3:2"}}, {"player": {"id": 47392, "name": "Pedro Le\u00f3n", "number": 21, "pos": "M", "grid": "3:1"}}, {"player": {"id": 47395, "name": "Sergi Enrich", "number": 9, "pos": "F", "grid": "4:2"}}, {"player": {"id": 47396, "name": "Kike", "number": 17, "pos": "F", "grid": "4:1"}}], "substitutes": [{"player": {"id": 47476, "name": "Yoel Rodr\u00edguez", "number": 13, "pos": "G", "grid": null}}, {"player": {"id": 47378, "name": "Pedro Bigas", "number": 3, "pos": "D", "grid": null}}, {"player": {"id": 46709, "name": "\u00c1lvaro Tejero", "number": 24, "pos": "D", "grid": null}}, {"player": {"id": 47382, "name": "Iv\u00e1n Ramis", "number": 4, "pos": "D", "grid": null}}, {"player": {"id": 46799, "name": "Edu Exp\u00f3sito", "number": 10, "pos": "M", "grid": null}}, {"player": {"id": 2600, "name": "Takashi Inui", "number": 22, "pos": "M", "grid": null}}, {"player": {"id": 47394, "name": "Charles D\u00edas", "number": 19, "pos": "F", "grid": null}}]}, {"team": {"id": 542, "name": "Alaves", "logo": "https://media-3.api-sports.io/football/teams/542.png", "colors": null}, "coach": {"id": 1591, "name": "Asier Garitano", "photo": "https://media-3.api-sports.io/football/coachs/1591.png"}, "formation": "4-2-3-1", "startXI": [{"player": {"id": 47352, "name": "Fernando Pacheco", "number": 1, "pos": "G", "grid": "1:1"}}, {"player": {"id": 47354, "name": "Mart\u00edn Aguirregabiria", "number": 21, "pos": "D", "grid": "2:4"}}, {"player": {"id": 47360, "name": "Ximo Navarro", "number": 23, "pos": "D", "grid": "2:3"}}, {"player": {"id": 47356, "name": "Rodrigo Ely", "number": 4, "pos": "D", "grid": "2:2"}}, {"player": {"id": 47355, "name": "Rub\u00e9n Duarte", "number": 3, "pos": "D", "grid": "2:1"}}, {"player": {"id": 3426, "name": "Mubarak Wakaso", "number": 22, "pos": "M", "grid": "3:2"}}, {"player": {"id": 47365, "name": "Tom\u00e1s Pina", "number": 8, "pos": "M", "grid": "3:1"}}, {"player": {"id": 133453, "name": "Borja Sainz", "number": 29, "pos": "M", "grid": "4:3"}}, {"player": {"id": 2047, "name": "Aleix Vidal", "number": 18, "pos": "M", "grid": "4:2"}}, {"player": {"id": 1124, "name": "Oliver Burke", "number": 24, "pos": "M", "grid": "4:1"}}, {"player": {"id": 18833, "name": "Lucas P\u00e9rez", "number": 7, "pos": "F", "grid": "5:1"}}], "substitutes": [{"player": {"id": 47353, "name": "Antonio Sivera", "number": 13, "pos": "G", "grid": null}}, {"player": {"id": 534, "name": "Lisandro Magall\u00e1n", "number": 6, "pos": "D", "grid": null}}, {"player": {"id": 47362, "name": "Burgui", "number": 14, "pos": "M", "grid": null}}, {"player": {"id": 47518, "name": "Pere Pons", "number": 20, "pos": "M", "grid": null}}, {"player": {"id": 47371, "name": "John Guidetti", "number": 10, "pos": "F", "grid": null}}, {"player": {"id": 18907, "name": "Joselu", "number": 9, "pos": "F", "grid": null}}, {"player": {"id": 46933, "name": "Luis Rioja", "number": 11, "pos": "F", "grid": null}}]}], "statistics": [{"team": {"id": 545, "name": "Eibar", "logo": "https://media-2.api-sports.io/football/teams/545.png"}, "statistics": [{"type": "Shots on Goal", "value": 7}, {"type": "Shots off Goal", "value": 6}, {"type": "Total Shots", "value": 19}, {"type": "Blocked Shots", "value": 6}, {"type": "Shots insidebox", "value": 11}, {"type": "Shots outsidebox", "value": 8}, {"type": "Fouls", "value": 10}, {"type": "Corner Kicks", "value": 10}, {"type": "Offsides", "value": 1}, {"type": "Ball Possession", "value": "58%"}, {"type": "Yellow Cards", "value": 1}, {"type": "Red Cards", "value": null}, {"type": "Goalkeeper Saves", "value": 4}, {"type": "Total passes", "value": 384}, {"type": "Passes accurate", "value": 257}, {"type": "Passes %", "value": "67%"}]}, {"team": {"id": 542, "name": "Alaves", "logo": "https://media-2.api-sports.io/football/teams/542.png"}, "statistics": [{"type": "Shots on Goal", "value": 5}, {"type": "Shots off Goal", "value": 2}, {"type": "Total Shots", "value": 7}, {"type": "Blocked Shots", "value": null}, {"type": "Shots insidebox", "value": 7}, {"type": "Shots outsidebox", "value": null}, {"type": "Fouls", "value": 11}, {"type": "Corner Kicks", "value": 4}, {"type": "Offsides", "value": 1}, {"type": "Ball Possession", "value": "42%"}, {"type": "Yellow Cards", "value": 2}, {"type": "Red Cards", "value": null}, {"type": "Goalkeeper Saves", "value": 7}, {"type": "Total passes", "value": 290}, {"type": "Passes accurate", "value": 166}, {"type": "Passes %", "value": "57%"}]}], "players": [{"team": {"id": 545, "name": "Eibar", "logo": "https://media-2.api-sports.io/football/teams/545.png", "update": "2020-05-13T18:14:55+00:00"}, "players": [{"player": {"id": 2813, "name": "Marko Dmitrovi\u0107", "photo": "https://media-1.api-sports.io/football/players/2813.png"}, "statistics": [{"games": {"minutes": 90, "number": 1, "position": "G", "rating": "6.8", "captain": false, "substitute": false}, "offsides": null, "shots": {"total": 0, "on": 0}, "goals": {"total": null, "conceded": 2, "assists": null, "saves": 4}, "passes": {"total": 11, "key": 0, "accuracy": "57%"}, "tackles": {"total": null, "blocks": 0, "interceptions": 1}, "duels": {"total": null, "won": null}, "dribbles": {"attempts": 0, "success": 0, "past": null}, "fouls": {"drawn": 0, "committed": 0}, "cards": {"yellow": 0, "red": 0}, "penalty": {"won": null, "commited": null, "scored": 0, "missed": 0, "saved": 0}}]}, {"player": {"id": 47386, "name": "Pablo De Blasis", "photo": "https://media-2.api-sports.io/football/players/47386.png"}, "statistics": [{"games": {"minutes": 90, "number": 16, "position": "D", "rating": "6.3", "captain": false, "substitute": false}, "offsides": null, "shots": {"total": 0, "on": 0}, "goals": {"total": null, "conceded": 0, "assists": null, "saves": null}, "passes": {"total": 27, "key": 1, "accuracy": "60%"}, "tackles": {"total": 1, "blocks": 0, "interceptions": 0}, "duels": {"total": null, "won": null}, "dribbles": {"attempts": 0, "success": 0, "past": 1}, "fouls": {"drawn": 0, "committed": 2}, "cards": {"yellow": 0, "red": 0}, "penalty": {"won": null, "commited": null, "scored": 0, "missed": 0, "saved": null}}]}, {"player": {"id": 47383, "name": "Paulo Oliveira", "photo": "https://media-2.api-sports.io/football/players/47383.png"}, "statistics": [{"games": {"minutes": 90, "number": 12, "position": "D", "rating": "6.8", "captain": false, "substitute": false}, "offsides": null, "shots": {"total": 1, "on": 0}, "goals": {"total": null, "conceded": 0, "assists": null, "saves": null}, "passes": {"total": 26, "key": 1, "accuracy": "63%"}, "tackles": {"total": 1, "blocks": 0, "interceptions": 1}, "duels": {"total": null, "won": null}, "dribbles": {"attempts": 0, "success": 0, "past": null}, "fouls": {"drawn": 1, "committed": 2}, "cards": {"yellow": 0, "red": 0}, "penalty": {"won": null, "commited": null, "scored": 0, "missed": 0, "saved": null}}]}, {"player": {"id": 47377, "name": "Anaitz Arbilla", "photo": "https://media-1.api-sports.io/football/players/47377.png"}, "statistics": [{"games": {"minutes": 90, "number": 23, "position": "D", "rating": "6.7", "captain": false, "substitute": false}, "offsides": null, "shots": {"total": 0, "on": 0}, "goals": {"total": null, "conceded": 0, "assists": null, "saves": null}, "passes": {"total": 39, "key": 1, "accuracy": "73%"}, "tackles": {"total": null, "blocks": 0, "interceptions": 2}, "duels": {"total": null, "won": null}, "dribbles": {"attempts": 0, "success": 0, "past": 2}, "fouls": {"drawn": 0, "committed": 2}, "cards": {"yellow": 1, "red": 0}, "penalty": {"won": null, "commited": null, "scored": 0, "missed": 0, "saved": null}}]}, {"player": {"id": 47384, "name": "Jos\u00e9 \u00c1ngel", "photo": "https://media-3.api-sports.io/football/players/47384.png"}, "statistics": [{"games": {"minutes": 81, "number": 15, "position": "D", "rating": "7.5", "captain": false, "substitute": false}, "offsides": null, "shots": {"total": 2, "on": 2}, "goals": {"total": null, "conceded": 0, "assists": null, "saves": null}, "passes": {"total": 24, "key": 0, "accuracy": "66%"}, "tackles": {"total": 3, "blocks": 0, "interceptions": 3}, "duels": {"total": null, "won": null}, "dribbles": {"attempts": 1, "success": 1, "past": null}, "fouls": {"drawn": 2, "committed": 1}, "cards": {"yellow": 0, "red": 0}, "penalty": {"won": null, "commited": null, "scored": 0, "missed": 0, "saved": null}}]}, {"player": {"id": 47390, "name": "Fabi\u00e1n Orellana", "photo": "https://media-3.api-sports.io/football/players/47390.png"}, "statistics": [{"games": {"minutes": 90, "number": 14, "position": "M", "rating": "6.7", "captain": false, "substitute": false}, "offsides": null, "shots": {"total": 2, "on": 1}, "goals": {"total": null, "conceded": 0, "assists": null, "saves": null}, "passes": {"total": 21, "key": 4, "accuracy": "77%"}, "tackles": {"total": 1, "blocks": 0, "interceptions": 0}, "duels": {"total": null, "won": null}, "dribbles": {"attempts": 8, "success": 7, "past": 2}, "fouls": {"drawn": 1, "committed": 0}, "cards": {"yellow": 0, "red": 0}, "penalty": {"won": null, "commited": null, "scored": 0, "missed": 0, "saved": null}}]}, {"player": {"id": 47387, "name": "Papakouli Diop", "photo": "https://media-2.api-sports.io/football/players/47387.png"}, "statistics": [{"games": {"minutes": 87, "number": 8, "position": "M", "rating": "6.3", "captain": false, "substitute": false}, "offsides": null, "shots": {"total": 2, "on": 0}, "goals": {"total": null, "conceded": 0, "assists": null, "saves": null}, "passes": {"total": 23, "key": 0, "accuracy": "67%"}, "tackles": {"total": null, "blocks": 0, "interceptions": 2}, "duels": {"total": null, "won": null}, "dribbles": {"attempts": 0, "success": 0, "past": 1}, "fouls": {"drawn": 0, "committed": 0}, "cards": {"yellow": 0, "red": 0}, "penalty": {"won": null, "commited": null, "scored": 0, "missed": 0, "saved": null}}]}, {"player": {"id": 47388, "name": "Gonzalo Escalante", "photo": "https://media-1.api-sports.io/football/players/47388.png"}, "statistics": [{"games": {"minutes": 90, "number": 5, "position": "M", "rating": "7.5", "captain": true, "substitute": false}, "offsides": null, "shots": {"total": 2, "on": 2}, "goals": {"total": null, "conceded": 0, "assists": null, "saves": null}, "passes": {"total": 27, "key": 0, "accuracy": "77%"}, "tackles": {"total": 5, "blocks": 0, "interceptions": 5}, "duels": {"total": null, "won": null}, "dribbles": {"attempts": 1, "success": 1, "past": 2}, "fouls": {"drawn": 1, "committed": 0}, "cards": {"yellow": 0, "red": 0}, "penalty": {"won": null, "commited": null, "scored": 0, "missed": 0, "saved": null}}]}, {"player": {"id": 47392, "name": "Pedro Le\u00f3n", "photo": "https://media-3.api-sports.io/football/players/47392.png"}, "statistics": [{"games": {"minutes": 90, "number": 21, "position": "M", "rating": "7.3", "captain": false, "substitute": false}, "offsides": null, "shots": {"total": 4, "on": 0}, "goals": {"total": null, "conceded": 0, "assists": null, "saves": null}, "passes": {"total": 20, "key": 2, "accuracy": "64%"}, "tackles": {"total": 2, "blocks": 0, "interceptions": 0}, "duels": {"total": null, "won": null}, "dribbles": {"attempts": 1, "success": 1, "past": 1}, "fouls": {"drawn": 2, "committed": 0}, "cards": {"yellow": 0, "red": 0}, "penalty": {"won": null, "commited": null, "scored": 0, "missed": 0, "saved": null}}]}, {"player": {"id": 47395, "name": "Sergi Enrich", "photo": "https://media-1.api-sports.io/football/players/47395.png"}, "statistics": [{"games": {"minutes": 65, "number": 9, "position": "F", "rating": "6.6", "captain": false, "substitute": false}, "offsides": null, "shots": {"total": 0, "on": 0}, "goals": {"total": null, "conceded": 0, "assists": null, "saves": null}, "passes": {"total": 14, "key": 0, "accuracy": "70%"}, "tackles": {"total": null, "blocks": 0, "interceptions": 1}, "duels": {"total": null, "won": null}, "dribbles": {"attempts": 1, "success": 0, "past": 1}, "fouls": {"drawn": 4, "committed": 2}, "cards": {"yellow": 0, "red": 0}, "penalty": {"won": null, "commited": null, "scored": 0, "missed": 0, "saved": null}}]}, {"player": {"id": 47396, "name": "Kike", "photo": "https://media-1.api-sports.io/football/players/47396.png"}, "statistics": [{"games": {"minutes": 90, "number": 17, "position": "F", "rating": "6.0", "captain": false, "substitute": false}, "offsides": null, "shots": {"total": 5, "on": 1}, "goals": {"total": null, "conceded": 0, "assists": null, "saves": null}, "passes": {"total": 18, "key": 2, "accuracy": "64%"}, "tackles": {"total": null, "blocks": 0, "interceptions": 0}, "duels": {"total": null, "won": null}, "dribbles": {"attempts": 1, "success": 0, "past": null}, "fouls": {"drawn": 0, "committed": 0}, "cards": {"yellow": 0, "red": 0}, "penalty": {"won": null, "commited": null, "scored": 0, "missed": 0, "saved": null}}]}, {"player": {"id": 47378, "name": "Pedro Bigas", "photo": "https://media-1.api-sports.io/football/players/47378.png"}, "statistics": [{"games": {"minutes": 9, "number": 3, "position": "D", "rating": "6.1", "captain": false, "substitute": true}, "offsides": null, "shots": {"total": 0, "on": 0}, "goals": {"total": null, "conceded": 0, "assists": null, "saves": null}, "passes": {"total": 2, "key": 0, "accuracy": "66%"}, "tackles": {"total": null, "blocks": 0, "interceptions": 0}, "duels": {"total": null, "won": null}, "dribbles": {"attempts": 0, "success": 0, "past": null}, "fouls": {"drawn": 0, "committed": 0}, "cards": {"yellow": 0, "red": 0}, "penalty": {"won": null, "commited": null, "scored": 0, "missed": 0, "saved": null}}]}, {"player": {"id": 47382, "name": "Iv\u00e1n Ramis", "photo": "https://media-1.api-sports.io/football/players/47382.png"}, "statistics": [{"games": {"minutes": 3, "number": 4, "position": "D", "rating": "\u2013", "captain": false, "substitute": true}, "offsides": null, "shots": {"total": 0, "on": 0}, "goals": {"total": null, "conceded": 0, "assists": null, "saves": null}, "passes": {"total": 1, "key": 0, "accuracy": "100%"}, "tackles": {"total": null, "blocks": 0, "interceptions": 0}, "duels": {"total": null, "won": null}, "dribbles": {"attempts": 0, "success": 0, "past": null}, "fouls": {"drawn": 0, "committed": 0}, "cards": {"yellow": 0, "red": 0}, "penalty": {"won": null, "commited": null, "scored": 0, "missed": 0, "saved": null}}]}, {"player": {"id": 47394, "name": "Charles D\u00edas", "photo": "https://media-3.api-sports.io/football/players/47394.png"}, "statistics": [{"games": {"minutes": 25, "number": 19, "position": "F", "rating": "6.6", "captain": false, "substitute": true}, "offsides": null, "shots": {"total": 1, "on": 1}, "goals": {"total": null, "conceded": 0, "assists": null, "saves": null}, "passes": {"total": 4, "key": 0, "accuracy": "36%"}, "tackles": {"total": null, "blocks": 0, "interceptions": 0}, "duels": {"total": null, "won": null}, "dribbles": {"attempts": 0, "success": 0, "past": 1}, "fouls": {"drawn": 0, "committed": 1}, "cards": {"yellow": 0, "red": 0}, "penalty": {"won": null, "commited": null, "scored": 0, "missed": 0, "saved": null}}]}]}, {"team": {"id": 542, "name": "Alaves", "logo": "https://media-3.api-sports.io/football/teams/542.png", "update": "2020-05-13T18:14:55+00:00"}, "players": [{"player": {"id": 47352, "name": "Fernando Pacheco", "photo": "https://media-1.api-sports.io/football/players/47352.png"}, "statistics": [{"games": {"minutes": 90, "number": 1, "position": "G", "rating": "8.7", "captain": true, "substitute": false}, "offsides": null, "shots": {"total": 0, "on": 0}, "goals": {"total": null, "conceded": 0, "assists": null, "saves": 7}, "passes": {"total": 14, "key": 0, "accuracy": "43%"}, "tackles": {"total": null, "blocks": 0, "interceptions": 0}, "duels": {"total": null, "won": null}, "dribbles": {"attempts": 0, "success": 0, "past": null}, "fouls": {"drawn": 0, "committed": 0}, "cards": {"yellow": 0, "red": 0}, "penalty": {"won": null, "commited": null, "scored": 0, "missed": 0, "saved": 0}}]}, {"player": {"id": 47354, "name": "Mart\u00edn Aguirregabiria", "photo": "https://media-1.api-sports.io/football/players/47354.png"}, "statistics": [{"games": {"minutes": 90, "number": 21, "position": "D", "rating": "7.3", "captain": false, "substitute": false}, "offsides": null, "shots": {"total": 0, "on": 0}, "goals": {"total": null, "conceded": 0, "assists": null, "saves": null}, "passes": {"total": 14, "key": 0, "accuracy": "42%"}, "tackles": {"total": 2, "blocks": 2, "interceptions": 0}, "duels": {"total": null, "won": null}, "dribbles": {"attempts": 1, "success": 1, "past": null}, "fouls": {"drawn": 3, "committed": 2}, "cards": {"yellow": 0, "red": 0}, "penalty": {"won": null, "commited": null, "scored": 0, "missed": 0, "saved": null}}]}, {"player": {"id": 47360, "name": "Ximo Navarro", "photo": "https://media-2.api-sports.io/football/players/47360.png"}, "statistics": [{"games": {"minutes": 90, "number": 23, "position": "D", "rating": "7.9", "captain": false, "substitute": false}, "offsides": null, "shots": {"total": 0, "on": 0}, "goals": {"total": null, "conceded": 0, "assists": null, "saves": null}, "passes": {"total": 17, "key": 0, "accuracy": "63%"}, "tackles": {"total": 4, "blocks": 1, "interceptions": 3}, "duels": {"total": null, "won": null}, "dribbles": {"attempts": 1, "success": 1, "past": null}, "fouls": {"drawn": 0, "committed": 1}, "cards": {"yellow": 1, "red": 0}, "penalty": {"won": null, "commited": null, "scored": 0, "missed": 0, "saved": null}}]}, {"player": {"id": 47356, "name": "Rodrigo Ely", "photo": "https://media-2.api-sports.io/football/players/47356.png"}, "statistics": [{"games": {"minutes": 90, "number": 4, "position": "D", "rating": "7.6", "captain": false, "substitute": false}, "offsides": null, "shots": {"total": 0, "on": 0}, "goals": {"total": null, "conceded": 0, "assists": null, "saves": null}, "passes": {"total": 16, "key": 0, "accuracy": "64%"}, "tackles": {"total": 1, "blocks": 1, "interceptions": 3}, "duels": {"total": null, "won": null}, "dribbles": {"attempts": 0, "success": 0, "past": null}, "fouls": {"drawn": 0, "committed": 1}, "cards": {"yellow": 0, "red": 0}, "penalty": {"won": null, "commited": null, "scored": 0, "missed": 0, "saved": null}}]}, {"player": {"id": 47355, "name": "Rub\u00e9n Duarte", "photo": "https://media-3.api-sports.io/football/players/47355.png"}, "statistics": [{"games": {"minutes": 90, "number": 3, "position": "D", "rating": "6.8", "captain": false, "substitute": false}, "offsides": null, "shots": {"total": 0, "on": 0}, "goals": {"total": null, "conceded": 0, "assists": null, "saves": null}, "passes": {"total": 11, "key": 0, "accuracy": "47%"}, "tackles": {"total": 2, "blocks": 1, "interceptions": 0}, "duels": {"total": null, "won": null}, "dribbles": {"attempts": 0, "success": 0, "past": 3}, "fouls": {"drawn": 0, "committed": 0}, "cards": {"yellow": 0, "red": 0}, "penalty": {"won": null, "commited": null, "scored": 0, "missed": 0, "saved": null}}]}, {"player": {"id": 3426, "name": "Mubarak Wakaso", "photo": "https://media-1.api-sports.io/football/players/3426.png"}, "statistics": [{"games": {"minutes": 89, "number": 22, "position": "M", "rating": "7.5", "captain": false, "substitute": false}, "offsides": null, "shots": {"total": 0, "on": 0}, "goals": {"total": null, "conceded": 0, "assists": null, "saves": null}, "passes": {"total": 17, "key": 0, "accuracy": "51%"}, "tackles": {"total": 7, "blocks": 1, "interceptions": 2}, "duels": {"total": null, "won": null}, "dribbles": {"attempts": 2, "success": 2, "past": 2}, "fouls": {"drawn": 1, "committed": 1}, "cards": {"yellow": 1, "red": 0}, "penalty": {"won": null, "commited": null, "scored": 0, "missed": 0, "saved": null}}]}, {"player": {"id": 47365, "name": "Tom\u00e1s Pina", "photo": "https://media-3.api-sports.io/football/players/47365.png"}, "statistics": [{"games": {"minutes": 90, "number": 8, "position": "M", "rating": "7.3", "captain": false, "substitute": false}, "offsides": null, "shots": {"total": 0, "on": 0}, "goals": {"total": null, "conceded": 0, "assists": null, "saves": null}, "passes": {"total": 21, "key": 0, "accuracy": "75%"}, "tackles": {"total": 2, "blocks": 0, "interceptions": 4}, "duels": {"total": null, "won": null}, "dribbles": {"attempts": 1, "success": 1, "past": null}, "fouls": {"drawn": 0, "committed": 1}, "cards": {"yellow": 0, "red": 0}, "penalty": {"won": null, "commited": null, "scored": 0, "missed": 0, "saved": null}}]}, {"player": {"id": 133453, "name": "Borja Sainz", "photo": "https://media-3.api-sports.io/football/players/133453.png"}, "statistics": [{"games": {"minutes": 65, "number": 29, "position": "M", "rating": "5.9", "captain": false, "substitute": false}, "offsides": null, "shots": {"total": 1, "on": 1}, "goals": {"total": null, "conceded": 0, "assists": null, "saves": null}, "passes": {"total": 5, "key": 1, "accuracy": "55%"}, "tackles": {"total": null, "blocks": 0, "interceptions": 0}, "duels": {"total": null, "won": null}, "dribbles": {"attempts": 2, "success": 0, "past": 1}, "fouls": {"drawn": 1, "committed": 2}, "cards": {"yellow": 0, "red": 0}, "penalty": {"won": null, "commited": null, "scored": 0, "missed": 0, "saved": null}}]}, {"player": {"id": 2047, "name": "Aleix Vidal", "photo": "https://media-2.api-sports.io/football/players/2047.png"}, "statistics": [{"games": {"minutes": 90, "number": 18, "position": "M", "rating": "7.5", "captain": false, "substitute": false}, "offsides": null, "shots": {"total": 2, "on": 2}, "goals": {"total": null, "conceded": 0, "assists": 1, "saves": null}, "passes": {"total": 26, "key": 2, "accuracy": "76%"}, "tackles": {"total": 1, "blocks": 0, "interceptions": 0}, "duels": {"total": null, "won": null}, "dribbles": {"attempts": 4, "success": 2, "past": 1}, "fouls": {"drawn": 1, "committed": 0}, "cards": {"yellow": 0, "red": 0}, "penalty": {"won": null, "commited": null, "scored": 0, "missed": 0, "saved": null}}]}, {"player": {"id": 1124, "name": "Oliver Burke", "photo": "https://media-2.api-sports.io/football/players/1124.png"}, "statistics": [{"games": {"minutes": 90, "number": 24, "position": "M", "rating": "6.6", "captain": false, "substitute": false}, "offsides": null, "shots": {"total": 2, "on": 0}, "goals": {"total": null, "conceded": 0, "assists": null, "saves": null}, "passes": {"total": 7, "key": 0, "accuracy": "38%"}, "tackles": {"total": 2, "blocks": 0, "interceptions": 1}, "duels": {"total": null, "won": null}, "dribbles": {"attempts": 5, "success": 3, "past": 2}, "fouls": {"drawn": 2, "committed": 2}, "cards": {"yellow": 0, "red": 0}, "penalty": {"won": null, "commited": null, "scored": 0, "missed": 0, "saved": null}}]}, {"player": {"id": 18833, "name": "Lucas P\u00e9rez", "photo": "https://media-3.api-sports.io/football/players/18833.png"}, "statistics": [{"games": {"minutes": 73, "number": 7, "position": "F", "rating": "6.5", "captain": false, "substitute": false}, "offsides": null, "shots": {"total": 0, "on": 0}, "goals": {"total": null, "conceded": 0, "assists": null, "saves": null}, "passes": {"total": 8, "key": 1, "accuracy": "72%"}, "tackles": {"total": null, "blocks": 0, "interceptions": 0}, "duels": {"total": null, "won": null}, "dribbles": {"attempts": 2, "success": 1, "past": null}, "fouls": {"drawn": 0, "committed": 0}, "cards": {"yellow": 0, "red": 0}, "penalty": {"won": null, "commited": null, "scored": 0, "missed": 0, "saved": null}}]}, {"player": {"id": 534, "name": "Lisandro Magall\u00e1n", "photo": "https://media-1.api-sports.io/football/players/534.png"}, "statistics": [{"games": {"minutes": 1, "number": 6, "position": "D", "rating": "\u2013", "captain": false, "substitute": false}, "offsides": null, "shots": {"total": 0, "on": 0}, "goals": {"total": null, "conceded": 0, "assists": null, "saves": null}, "passes": {"total": 0, "key": 0, "accuracy": "0%"}, "tackles": {"total": null, "blocks": 0, "interceptions": 0}, "duels": {"total": null, "won": null}, "dribbles": {"attempts": 0, "success": 0, "past": null}, "fouls": {"drawn": 0, "committed": 0}, "cards": {"yellow": 0, "red": 0}, "penalty": {"won": null, "commited": null, "scored": 0, "missed": 0, "saved": null}}]}, {"player": {"id": 47518, "name": "Pere Pons", "photo": "https://media-2.api-sports.io/football/players/47518.png"}, "statistics": [{"games": {"minutes": 25, "number": 20, "position": "M", "rating": "7.3", "captain": false, "substitute": false}, "offsides": null, "shots": {"total": 0, "on": 0}, "goals": {"total": null, "conceded": 0, "assists": 1, "saves": null}, "passes": {"total": 5, "key": 2, "accuracy": "71%"}, "tackles": {"total": null, "blocks": 0, "interceptions": 0}, "duels": {"total": null, "won": null}, "dribbles": {"attempts": 1, "success": 0, "past": 1}, "fouls": {"drawn": 0, "committed": 1}, "cards": {"yellow": 0, "red": 0}, "penalty": {"won": null, "commited": null, "scored": 0, "missed": 0, "saved": null}}]}, {"player": {"id": 18907, "name": "Joselu", "photo": "https://media-1.api-sports.io/football/players/18907.png"}, "statistics": [{"games": {"minutes": 17, "number": 9, "position": "F", "rating": "8.9", "captain": false, "substitute": false}, "offsides": null, "shots": {"total": 2, "on": 2}, "goals": {"total": 2, "conceded": 0, "assists": null, "saves": null}, "passes": {"total": 5, "key": 0, "accuracy": "50%"}, "tackles": {"total": 3, "blocks": 0, "interceptions": 0}, "duels": {"total": null, "won": null}, "dribbles": {"attempts": 0, "success": 0, "past": null}, "fouls": {"drawn": 1, "committed": 0}, "cards": {"yellow": 0, "red": 0}, "penalty": {"won": null, "commited": null, "scored": 0, "missed": 0, "saved": null}}]}]}]}]}