{"get": "fixtures", "parameters": {"id": "9547"}, "errors": [], "results": 1, "paging": {"current": 1, "total": 1}, "response": [{"fixture": {"id": 9547, "referee": "Jose Maria Sanchez Martinez, Spain", "timezone": "UTC", "date": "2018-04-28T14:15:00+00:00", "timestamp": 1524924900, "periods": {"first": 1524924900, "second": 1524928500}, "venue": {"id": null, "name": "Anoeta", "city": "San Sebastian"}, "status": {"long": "Match Finished", "short": "FT", "elapsed": 90}}, "league": {"id": 140, "name": "La Liga", "country": "Spain", "logo": "https://media-2.api-sports.io/football/leagues/140.png", "flag": "https://media-2.api-sports.io/flags/es.svg", "season": 2017, "round": "Regular Season - 35"}, "teams": {"home": {"id": 548, "name": "Real Sociedad", "logo": "https://media-1.api-sports.io/football/teams/548.png", "winner": true}, "away": {"id": 531, "name": "Athletic Club", "logo": "https://media-3.api-sports.io/football/teams/531.png", "winner": false}}, "goals": {"home": 3, "away": 1}, "score": {"halftime": {"home": 2, "away": 0}, "fulltime": {"home": 3, "away": 1}, "extratime": {"home": null, "away": null}, "penalty": {"home": null, "away": null}}, "events": [{"time": {"elapsed": 13, "extra": null}, "team": {"id": 531, "name": "Athletic Club", "logo": "https://media-1.api-sports.io/football/teams/531.png"}, "player": {"id": 47282, "name": "Raúl García"}, "assist": {"id": null, "name": null}, "type": "Card", "detail": "Yellow Card", "comments": null}, {"time": {"elapsed": 15, "extra": null}, "team": {"id": 548, "name": "Real Sociedad", "logo": "https://media-3.api-sports.io/football/teams/548.png"}, "player": {"id": 47288, "name": "San José"}, "assist": {"id": null, "name": null}, "type": "Goal", "detail": "Own Goal", "comments": null}, {"time": {"elapsed": 24, "extra": null}, "team": {"id": 531, "name": "Athletic Club", "logo": "https://media-2.api-sports.io/football/teams/531.png"}, "player": {"id": 47275, "name": "Óscar de Marcos"}, "assist": {"id": null, "name": null}, "type": "Card", "detail": "Yellow Card", "comments": null}, {"time": {"elapsed": 26, "extra": null}, "team": {"id": 548, "name": "Real Sociedad", "logo": "https://media-1.api-sports.io/football/teams/548.png"}, "player": {"id": 47310, "name": "Asier Illarramendi"}, "assist": {"id": null, "name": null}, "type": "Card", "detail": "Yellow Card", "comments": null}, {"time": {"elapsed": 36, "extra": null}, "team": {"id": 548, "name": "Real Sociedad", "logo": "https://media-1.api-sports.io/football/teams/548.png"}, "player": {"id": 47323, "name": "Mikel Oyarzabal"}, "assist": {"id": 2924, "name": "A. Januzaj"}, "type": "Goal", "detail": "Normal Goal", "comments": null}, {"time": {"elapsed": 50, "extra": null}, "team": {"id": 531, "name": "Athletic Club", "logo": "https://media-2.api-sports.io/football/teams/531.png"}, "player": {"id": 47276, "name": "Lekue"}, "assist": {"id": 47289, "name": "Susaeta"}, "type": "subst", "detail": "Substitution 1", "comments": null}, {"time": {"elapsed": 54, "extra": null}, "team": {"id": 548, "name": "Real Sociedad", "logo": "https://media-2.api-sports.io/football/teams/548.png"}, "player": {"id": 47288, "name": "San José"}, "assist": {"id": null, "name": null}, "type": "Goal", "detail": "Own Goal", "comments": null}, {"time": {"elapsed": 59, "extra": null}, "team": {"id": 548, "name": "Real Sociedad", "logo": "https://media-3.api-sports.io/football/teams/548.png"}, "player": {"id": 47302, "name": "Diego Llorente"}, "assist": {"id": null, "name": null}, "type": "Card", "detail": "Yellow Card", "comments": null}, {"time": {"elapsed": 59, "extra": null}, "team": {"id": 531, "name": "Athletic Club", "logo": "https://media-2.api-sports.io/football/teams/531.png"}, "player": {"id": 47282, "name": "Raúl García"}, "assist": {"id": null, "name": null}, "type": "Goal", "detail": "Penalty", "comments": null}, {"time": {"elapsed": 68, "extra": null}, "team": {"id": 531, "name": "Athletic Club", "logo": "https://media-3.api-sports.io/football/teams/531.png"}, "player": {"id": 47279, "name": "Iñigo Córdoba"}, "assist": {"id": 2672, "name": "Muniain"}, "type": "subst", "detail": "Substitution 2", "comments": null}, {"time": {"elapsed": 73, "extra": null}, "team": {"id": 531, "name": "Athletic Club", "logo": "https://media-2.api-sports.io/football/teams/531.png"}, "player": {"id": 47284, "name": "Iturraspe"}, "assist": {"id": 47287, "name": "Mikel Rico"}, "type": "subst", "detail": "Substitution 3", "comments": null}, {"time": {"elapsed": 79, "extra": null}, "team": {"id": 548, "name": "Real Sociedad", "logo": "https://media-3.api-sports.io/football/teams/548.png"}, "player": {"id": 1570, "name": "Canales"}, "assist": {"id": 47312, "name": "Rubén Pardo"}, "type": "subst", "detail": "Substitution 1", "comments": null}, {"time": {"elapsed": 81, "extra": null}, "team": {"id": 531, "name": "Athletic Club", "logo": "https://media-1.api-sports.io/football/teams/531.png"}, "player": {"id": 47294, "name": "Iñaki Williams"}, "assist": {"id": null, "name": null}, "type": "Card", "detail": "Yellow Card", "comments": null}, {"time": {"elapsed": 83, "extra": null}, "team": {"id": 548, "name": "Real Sociedad", "logo": "https://media-1.api-sports.io/football/teams/548.png"}, "player": {"id": 47298, "name": "Aritz Elustondo"}, "assist": {"id": 737, "name": "Álvaro Odriozola"}, "type": "subst", "detail": "Substitution 2", "comments": null}, {"time": {"elapsed": 84, "extra": null}, "team": {"id": 531, "name": "Athletic Club", "logo": "https://media-3.api-sports.io/football/teams/531.png"}, "player": {"id": 47289, "name": "Markel Susaeta"}, "assist": {"id": null, "name": null}, "type": "Card", "detail": "Yellow Card", "comments": null}, {"time": {"elapsed": 85, "extra": null}, "team": {"id": 548, "name": "Real Sociedad", "logo": "https://media-3.api-sports.io/football/teams/548.png"}, "player": {"id": 47312, "name": "Rubén Pardo"}, "assist": {"id": null, "name": null}, "type": "Card", "detail": "Red Card", "comments": null}, {"time": {"elapsed": 86, "extra": null}, "team": {"id": 531, "name": "Athletic Club", "logo": "https://media-3.api-sports.io/football/teams/531.png"}, "player": {"id": 2672, "name": "Iker Muniain"}, "assist": {"id": null, "name": null}, "type": "Card", "detail": "Yellow Card", "comments": null}, {"time": {"elapsed": 86, "extra": null}, "team": {"id": 548, "name": "Real Sociedad", "logo": "https://media-2.api-sports.io/football/teams/548.png"}, "player": {"id": 47319, "name": "Willian José"}, "assist": {"id": null, "name": null}, "type": "Card", "detail": "Yellow Card", "comments": null}, {"time": {"elapsed": 90, "extra": null}, "team": {"id": 548, "name": "Real Sociedad", "logo": "https://media-3.api-sports.io/football/teams/548.png"}, "player": {"id": 2924, "name": "A. Januzaj"}, "assist": {"id": 47314, "name": "Igor Zubeldía"}, "type": "subst", "detail": "Substitution 3", "comments": null}, {"time": {"elapsed": 90, "extra": null}, "team": {"id": 531, "name": "Athletic Club", "logo": "https://media-1.api-sports.io/football/teams/531.png"}, "player": {"id": 2670, "name": "Iñigo Martínez"}, "assist": {"id": null, "name": null}, "type": "Card", "detail": "Yellow Card", "comments": null}], "lineups": [{"team": {"id": 548, "name": "Real Sociedad", "logo": "https://media-3.api-sports.io/football/teams/548.png", "colors": null}, "coach": {"id": 1586, "name": "Imanol Alguacil", "photo": "https://media-1.api-sports.io/football/coachs/1586.png"}, "formation": "4-2-3-1", "startXI": [{"player": {"id": 47295, "name": "Moyà", "number": 25, "pos": "G", "grid": "1:1"}}, {"player": {"id": 46994, "name": "De La Bella", "number": 24, "pos": "D", "grid": "2:4"}}, {"player": {"id": 47305, "name": "Raúl Navas", "number": 22, "pos": "D", "grid": "2:3"}}, {"player": {"id": 47302, "name": "Diego Llorente", "number": 3, "pos": "D", "grid": "2:2"}}, {"player": {"id": 47298, "name": "Aritz Elustondo", "number": 15, "pos": "D", "grid": "2:1"}}, {"player": {"id": 1570, "name": "Canales", "number": 16, "pos": "M", "grid": "3:2"}}, {"player": {"id": 47310, "name": "Illarramendi", "number": 4, "pos": "M", "grid": "3:1"}}, {"player": {"id": 47316, "name": "Zurutuza", "number": 17, "pos": "M", "grid": "4:3"}}, {"player": {"id": 2924, "name": "A. Januzaj", "number": 8, "pos": "M", "grid": "4:2"}}, {"player": {"id": 47319, "name": "Willian José", "number": 12, "pos": "F", "grid": "4:1"}}, {"player": {"id": 47323, "name": "Mikel Oyarzabal", "number": 18, "pos": "M", "grid": "5:1"}}], "substitutes": [{"player": {"id": 47312, "name": "Rubén Pardo", "number": 14, "pos": "M", "grid": null}}, {"player": {"id": 737, "name": "Álvaro Odriozola", "number": 19, "pos": "D", "grid": null}}, {"player": {"id": 47314, "name": "Igor Zubeldía", "number": 5, "pos": "M", "grid": null}}, {"player": {"id": 47320, "name": "Juanmi", "number": 7, "pos": "F", "grid": null}}, {"player": {"id": 47304, "name": "Kévin Rodrigues", "number": 20, "pos": "D", "grid": null}}, {"player": {"id": 47318, "name": "Jon Bautista", "number": 21, "pos": "F", "grid": null}}, {"player": {"id": 47296, "name": "G. Rulli", "number": 1, "pos": "G", "grid": null}}]}, {"team": {"id": 531, "name": "Athletic Club", "logo": "https://media-1.api-sports.io/football/teams/531.png", "colors": null}, "coach": {"id": 8675, "name": "José Ángel Ziganda", "photo": "https://media-2.api-sports.io/football/coachs/8675.png"}, "formation": "4-2-3-1", "startXI": [{"player": {"id": 2273, "name": "Kepa", "number": 1, "pos": "G", "grid": "1:1"}}, {"player": {"id": 47272, "name": "Balenziaga", "number": 24, "pos": "D", "grid": "2:4"}}, {"player": {"id": 47275, "name": "De Marcos", "number": 18, "pos": "D", "grid": "2:3"}}, {"player": {"id": 2670, "name": "Íñigo Martínez", "number": 4, "pos": "D", "grid": "2:2"}}, {"player": {"id": 47276, "name": "Lekue", "number": 15, "pos": "D", "grid": "2:1"}}, {"player": {"id": 47277, "name": "Unai Núñez", "number": 12, "pos": "D", "grid": "3:2"}}, {"player": {"id": 47282, "name": "Raúl García", "number": 22, "pos": "M", "grid": "3:1"}}, {"player": {"id": 47288, "name": "San José", "number": 6, "pos": "M", "grid": "4:3"}}, {"player": {"id": 47284, "name": "Iturraspe", "number": 8, "pos": "M", "grid": "4:2"}}, {"player": {"id": 47279, "name": "Iñigo Córdoba", "number": 28, "pos": "M", "grid": "4:1"}}, {"player": {"id": 47294, "name": "Iñaki Williams", "number": 11, "pos": "F", "grid": "5:1"}}], "substitutes": [{"player": {"id": 47289, "name": "Susaeta", "number": 14, "pos": "M", "grid": null}}, {"player": {"id": 2672, "name": "Muniain", "number": 10, "pos": "F", "grid": null}}, {"player": {"id": 47287, "name": "Mikel Rico", "number": 17, "pos": "M", "grid": null}}, {"player": {"id": 47271, "name": "Yeray Álvarez", "number": 5, "pos": "D", "grid": null}}, {"player": {"id": 47280, "name": "Beñat", "number": 7, "pos": "M", "grid": null}}, {"player": {"id": 47267, "name": "Iago Herrerín", "number": 13, "pos": "G", "grid": null}}, {"player": {"id": 47423, "name": "Sabin Merino", "number": 19, "pos": "F", "grid": null}}]}], "statistics": [{"team": {"id": 548, "name": "Real Sociedad", "logo": "https://media-3.api-sports.io/football/teams/548.png"}, "statistics": [{"type": "Shots on Goal", "value": 4}, {"type": "Shots off Goal", "value": 8}, {"type": "Total Shots", "value": 17}, {"type": "Blocked Shots", "value": 5}, {"type": "Shots insidebox", "value": 13}, {"type": "Shots outsidebox", "value": 6}, {"type": "Fouls", "value": 16}, {"type": "Corner Kicks", "value": 3}, {"type": "Offsides", "value": 3}, {"type": "Ball Possession", "value": "51%"}, {"type": "Yellow Cards", "value": 3}, {"type": "Red Cards", "value": 1}, {"type": "Goalkeeper Saves", "value": 2}, {"type": "Total passes", "value": 427}, {"type": "Passes accurate", "value": 339}, {"type": "Passes %", "value": "79%"}]}, {"team": {"id": 531, "name": "Athletic Club", "logo": "https://media-1.api-sports.io/football/teams/531.png"}, "statistics": [{"type": "Shots on Goal", "value": 3}, {"type": "Shots off Goal", "value": 3}, {"type": "Total Shots", "value": 9}, {"type": "Blocked Shots", "value": 3}, {"type": "Shots insidebox", "value": 8}, {"type": "Shots outsidebox", "value": 1}, {"type": "Fouls", "value": 16}, {"type": "Corner Kicks", "value": 7}, {"type": "Offsides", "value": 2}, {"type": "Ball Possession", "value": "49%"}, {"type": "Yellow Cards", "value": 6}, {"type": "Red Cards", "value": null}, {"type": "Goalkeeper Saves", "value": 3}, {"type": "Total passes", "value": 382}, {"type": "Passes accurate", "value": 282}, {"type": "Passes %", "value": "74%"}]}], "players": [{"team": {"id": 548, "name": "Real Sociedad", "logo": "https://media-3.api-sports.io/football/teams/548.png", "update": "2020-05-12T16:54:41+00:00"}, "players": [{"player": {"id": 47295, "name": "Miguel Ángel Moyà", "photo": "https://media-3.api-sports.io/football/players/47295.png"}, "statistics": [{"games": {"minutes": 90, "number": 25, "position": "G", "rating": "6.9", "captain": false, "substitute": false}, "offsides": null, "shots": {"total": 0, "on": 0}, "goals": {"total": null, "conceded": 1, "assists": null, "saves": 2}, "passes": {"total": 29, "key": 0, "accuracy": "74%"}, "tackles": {"total": null, "blocks": 0, "interceptions": 0}, "duels": {"total": 1, "won": 1}, "dribbles": {"attempts": 0, "success": 0, "past": null}, "fouls": {"drawn": 0, "committed": 0}, "cards": {"yellow": 0, "red": 0}, "penalty": {"won": null, "commited": null, "scored": 0, "missed": 0, "saved": 0}}]}, {"player": {"id": 47298, "name": "Aritz Elustondo", "photo": "https://media-2.api-sports.io/football/players/47298.png"}, "statistics": [{"games": {"minutes": 83, "number": 15, "position": "D", "rating": "6.6", "captain": false, "substitute": false}, "offsides": null, "shots": {"total": 2, "on": 1}, "goals": {"total": null, "conceded": null, "assists": null, "saves": null}, "passes": {"total": 20, "key": 0, "accuracy": "64%"}, "tackles": {"total": 1, "blocks": 0, "interceptions": 3}, "duels": {"total": 14, "won": 6}, "dribbles": {"attempts": 1, "success": 0, "past": 1}, "fouls": {"drawn": 0, "committed": 2}, "cards": {"yellow": 0, "red": 0}, "penalty": {"won": null, "commited": null, "scored": 0, "missed": 0, "saved": null}}]}, {"player": {"id": 47302, "name": "Diego Llorente", "photo": "https://media-3.api-sports.io/football/players/47302.png"}, "statistics": [{"games": {"minutes": 90, "number": 3, "position": "D", "rating": "7.1", "captain": false, "substitute": false}, "offsides": null, "shots": {"total": 3, "on": 1}, "goals": {"total": null, "conceded": null, "assists": null, "saves": null}, "passes": {"total": 33, "key": 0, "accuracy": "91%"}, "tackles": {"total": 1, "blocks": 1, "interceptions": 2}, "duels": {"total": 8, "won": 7}, "dribbles": {"attempts": 1, "success": 1, "past": null}, "fouls": {"drawn": 0, "committed": 1}, "cards": {"yellow": 1, "red": 0}, "penalty": {"won": null, "commited": 1, "scored": 0, "missed": 0, "saved": null}}]}, {"player": {"id": 47305, "name": "Raúl Navas", "photo": "https://media-2.api-sports.io/football/players/47305.png"}, "statistics": [{"games": {"minutes": 90, "number": 22, "position": "D", "rating": "6.8", "captain": false, "substitute": false}, "offsides": null, "shots": {"total": 1, "on": 0}, "goals": {"total": null, "conceded": null, "assists": null, "saves": null}, "passes": {"total": 47, "key": 0, "accuracy": "81%"}, "tackles": {"total": 1, "blocks": 1, "interceptions": 0}, "duels": {"total": 9, "won": 5}, "dribbles": {"attempts": 1, "success": 1, "past": 1}, "fouls": {"drawn": 0, "committed": 2}, "cards": {"yellow": 0, "red": 0}, "penalty": {"won": null, "commited": null, "scored": 0, "missed": 0, "saved": null}}]}, {"player": {"id": 46994, "name": "Alberto de la Bella", "photo": "https://media-1.api-sports.io/football/players/46994.png"}, "statistics": [{"games": {"minutes": 90, "number": 24, "position": "D", "rating": "6.3", "captain": false, "substitute": false}, "offsides": null, "shots": {"total": 0, "on": 0}, "goals": {"total": null, "conceded": null, "assists": null, "saves": null}, "passes": {"total": 30, "key": 0, "accuracy": "73%"}, "tackles": {"total": null, "blocks": 0, "interceptions": 1}, "duels": {"total": 9, "won": 3}, "dribbles": {"attempts": 1, "success": 0, "past": 1}, "fouls": {"drawn": 2, "committed": 1}, "cards": {"yellow": 0, "red": 0}, "penalty": {"won": null, "commited": null, "scored": 0, "missed": 0, "saved": null}}]}, {"player": {"id": 47310, "name": "Asier Illarramendi", "photo": "https://media-2.api-sports.io/football/players/47310.png"}, "statistics": [{"games": {"minutes": 90, "number": 4, "position": "M", "rating": "6.8", "captain": true, "substitute": false}, "offsides": null, "shots": {"total": 0, "on": 0}, "goals": {"total": null, "conceded": null, "assists": null, "saves": null}, "passes": {"total": 44, "key": 1, "accuracy": "95%"}, "tackles": {"total": 1, "blocks": 0, "interceptions": 3}, "duels": {"total": 9, "won": 4}, "dribbles": {"attempts": 1, "success": 0, "past": 2}, "fouls": {"drawn": 3, "committed": 1}, "cards": {"yellow": 1, "red": 0}, "penalty": {"won": null, "commited": null, "scored": 0, "missed": 0, "saved": null}}]}, {"player": {"id": 47316, "name": "David Zurutuza", "photo": "https://media-2.api-sports.io/football/players/47316.png"}, "statistics": [{"games": {"minutes": 90, "number": 17, "position": "M", "rating": "7.2", "captain": false, "substitute": false}, "offsides": null, "shots": {"total": 1, "on": 0}, "goals": {"total": null, "conceded": null, "assists": null, "saves": null}, "passes": {"total": 37, "key": 0, "accuracy": "88%"}, "tackles": {"total": 3, "blocks": 0, "interceptions": 2}, "duels": {"total": 18, "won": 11}, "dribbles": {"attempts": 1, "success": 1, "past": null}, "fouls": {"drawn": 6, "committed": 1}, "cards": {"yellow": 0, "red": 0}, "penalty": {"won": null, "commited": null, "scored": 0, "missed": 0, "saved": null}}]}, {"player": {"id": 2924, "name": "Adnan Januzaj", "photo": "https://media-1.api-sports.io/football/players/2924.png"}, "statistics": [{"games": {"minutes": 89, "number": 8, "position": "M", "rating": "7.2", "captain": false, "substitute": false}, "offsides": null, "shots": {"total": 3, "on": 1}, "goals": {"total": null, "conceded": null, "assists": 1, "saves": null}, "passes": {"total": 23, "key": 3, "accuracy": "82%"}, "tackles": {"total": null, "blocks": 0, "interceptions": 0}, "duels": {"total": 10, "won": 5}, "dribbles": {"attempts": 3, "success": 1, "past": 1}, "fouls": {"drawn": 4, "committed": 2}, "cards": {"yellow": 0, "red": 0}, "penalty": {"won": null, "commited": null, "scored": 0, "missed": 0, "saved": null}}]}, {"player": {"id": 1570, "name": "Sergio Canales", "photo": "https://media-3.api-sports.io/football/players/1570.png"}, "statistics": [{"games": {"minutes": 79, "number": 16, "position": "M", "rating": "7.1", "captain": false, "substitute": false}, "offsides": null, "shots": {"total": 3, "on": 0}, "goals": {"total": null, "conceded": null, "assists": null, "saves": null}, "passes": {"total": 29, "key": 5, "accuracy": "80%"}, "tackles": {"total": null, "blocks": 0, "interceptions": 0}, "duels": {"total": 7, "won": 1}, "dribbles": {"attempts": 0, "success": 0, "past": 2}, "fouls": {"drawn": 1, "committed": 0}, "cards": {"yellow": 0, "red": 0}, "penalty": {"won": null, "commited": null, "scored": 0, "missed": 0, "saved": null}}]}, {"player": {"id": 47323, "name": "Mikel Oyarzabal", "photo": "https://media-3.api-sports.io/football/players/47323.png"}, "statistics": [{"games": {"minutes": 90, "number": 18, "position": "M", "rating": "6.0", "captain": false, "substitute": false}, "offsides": null, "shots": {"total": 2, "on": 1}, "goals": {"total": 1, "conceded": null, "assists": null, "saves": null}, "passes": {"total": 23, "key": 0, "accuracy": "74%"}, "tackles": {"total": null, "blocks": 0, "interceptions": 1}, "duels": {"total": 17, "won": 3}, "dribbles": {"attempts": 3, "success": 1, "past": 4}, "fouls": {"drawn": 0, "committed": 1}, "cards": {"yellow": 0, "red": 0}, "penalty": {"won": null, "commited": null, "scored": 0, "missed": 0, "saved": null}}]}, {"player": {"id": 47319, "name": "Willian José", "photo": "https://media-2.api-sports.io/football/players/47319.png"}, "statistics": [{"games": {"minutes": 90, "number": 12, "position": "F", "rating": "6.6", "captain": false, "substitute": false}, "offsides": null, "shots": {"total": 2, "on": 0}, "goals": {"total": null, "conceded": null, "assists": null, "saves": null}, "passes": {"total": 21, "key": 4, "accuracy": "61%"}, "tackles": {"total": null, "blocks": 0, "interceptions": 0}, "duels": {"total": 13, "won": 1}, "dribbles": {"attempts": 1, "success": 0, "past": null}, "fouls": {"drawn": 0, "committed": 3}, "cards": {"yellow": 1, "red": 0}, "penalty": {"won": null, "commited": null, "scored": 0, "missed": 0, "saved": null}}]}, {"player": {"id": 737, "name": "Álvaro Odriozola", "photo": "https://media-1.api-sports.io/football/players/737.png"}, "statistics": [{"games": {"minutes": 7, "number": 19, "position": "D", "rating": "6.5", "captain": false, "substitute": true}, "offsides": null, "shots": {"total": 0, "on": 0}, "goals": {"total": null, "conceded": null, "assists": null, "saves": null}, "passes": {"total": 1, "key": 0, "accuracy": "33%"}, "tackles": {"total": null, "blocks": 0, "interceptions": 0}, "duels": {"total": 0, "won": 0}, "dribbles": {"attempts": 0, "success": 0, "past": null}, "fouls": {"drawn": 0, "committed": 0}, "cards": {"yellow": 0, "red": 0}, "penalty": {"won": null, "commited": null, "scored": 0, "missed": 0, "saved": null}}]}, {"player": {"id": 47314, "name": "Igor Zubeldia", "photo": "https://media-2.api-sports.io/football/players/47314.png"}, "statistics": [{"games": {"minutes": 1, "number": 5, "position": "M", "rating": "–", "captain": false, "substitute": true}, "offsides": null, "shots": {"total": 0, "on": 0}, "goals": {"total": null, "conceded": null, "assists": null, "saves": null}, "passes": {"total": 1, "key": 0, "accuracy": "100%"}, "tackles": {"total": null, "blocks": 0, "interceptions": 0}, "duels": {"total": 1, "won": 0}, "dribbles": {"attempts": 0, "success": 0, "past": null}, "fouls": {"drawn": 0, "committed": 1}, "cards": {"yellow": 0, "red": 0}, "penalty": {"won": null, "commited": null, "scored": 0, "missed": 0, "saved": null}}]}, {"player": {"id": 47312, "name": "Rubén Pardo", "photo": "https://media-1.api-sports.io/football/players/47312.png"}, "statistics": [{"games": {"minutes": 6, "number": 14, "position": "M", "rating": "5.3", "captain": false, "substitute": true}, "offsides": null, "shots": {"total": 0, "on": 0}, "goals": {"total": null, "conceded": null, "assists": null, "saves": null}, "passes": {"total": 1, "key": 0, "accuracy": "100%"}, "tackles": {"total": null, "blocks": 0, "interceptions": 1}, "duels": {"total": 4, "won": 1}, "dribbles": {"attempts": 2, "success": 1, "past": null}, "fouls": {"drawn": 0, "committed": 1}, "cards": {"yellow": 0, "red": 1}, "penalty": {"won": null, "commited": null, "scored": 0, "missed": 0, "saved": null}}]}]}, {"team": {"id": 531, "name": "Athletic Club", "logo": "https://media-2.api-sports.io/football/teams/531.png", "update": "2020-05-12T16:54:41+00:00"}, "players": [{"player": {"id": 2273, "name": "Kepa Arrizabalaga", "photo": "https://media-3.api-sports.io/football/players/2273.png"}, "statistics": [{"games": {"minutes": 90, "number": 1, "position": "G", "rating": "6.6", "captain": false, "substitute": false}, "offsides": null, "shots": {"total": 0, "on": 0}, "goals": {"total": null, "conceded": 3, "assists": null, "saves": 3}, "passes": {"total": 19, "key": 0, "accuracy": "57%"}, "tackles": {"total": null, "blocks": 0, "interceptions": 0}, "duels": {"total": 0, "won": 0}, "dribbles": {"attempts": 0, "success": 0, "past": null}, "fouls": {"drawn": 0, "committed": 0}, "cards": {"yellow": 0, "red": 0}, "penalty": {"won": null, "commited": null, "scored": 0, "missed": 0, "saved": 0}}]}, {"player": {"id": 47275, "name": "Óscar de Marcos", "photo": "https://media-3.api-sports.io/football/players/47275.png"}, "statistics": [{"games": {"minutes": 90, "number": 18, "position": "D", "rating": "6.8", "captain": false, "substitute": false}, "offsides": null, "shots": {"total": 0, "on": 0}, "goals": {"total": null, "conceded": null, "assists": null, "saves": null}, "passes": {"total": 36, "key": 0, "accuracy": "81%"}, "tackles": {"total": 3, "blocks": 0, "interceptions": 1}, "duels": {"total": 10, "won": 8}, "dribbles": {"attempts": 2, "success": 2, "past": null}, "fouls": {"drawn": 2, "committed": 1}, "cards": {"yellow": 1, "red": 0}, "penalty": {"won": null, "commited": null, "scored": 0, "missed": 0, "saved": null}}]}, {"player": {"id": 47277, "name": "Unai Núñez", "photo": "https://media-2.api-sports.io/football/players/47277.png"}, "statistics": [{"games": {"minutes": 90, "number": 12, "position": "D", "rating": "7.1", "captain": false, "substitute": false}, "offsides": null, "shots": {"total": 0, "on": 0}, "goals": {"total": null, "conceded": null, "assists": null, "saves": null}, "passes": {"total": 33, "key": 0, "accuracy": "80%"}, "tackles": {"total": 3, "blocks": 1, "interceptions": 4}, "duels": {"total": 12, "won": 9}, "dribbles": {"attempts": 0, "success": 0, "past": null}, "fouls": {"drawn": 1, "committed": 0}, "cards": {"yellow": 0, "red": 0}, "penalty": {"won": null, "commited": null, "scored": 0, "missed": 0, "saved": null}}]}, {"player": {"id": 2670, "name": "Iñigo Martínez", "photo": "https://media-3.api-sports.io/football/players/2670.png"}, "statistics": [{"games": {"minutes": 90, "number": 4, "position": "D", "rating": "6.6", "captain": false, "substitute": false}, "offsides": null, "shots": {"total": 3, "on": 0}, "goals": {"total": null, "conceded": null, "assists": null, "saves": null}, "passes": {"total": 35, "key": 0, "accuracy": "76%"}, "tackles": {"total": null, "blocks": 1, "interceptions": 2}, "duels": {"total": 5, "won": 3}, "dribbles": {"attempts": 2, "success": 2, "past": null}, "fouls": {"drawn": 0, "committed": 0}, "cards": {"yellow": 1, "red": 0}, "penalty": {"won": null, "commited": null, "scored": 0, "missed": 0, "saved": null}}]}, {"player": {"id": 47272, "name": "Mikel Balenziaga", "photo": "https://media-3.api-sports.io/football/players/47272.png"}, "statistics": [{"games": {"minutes": 90, "number": 24, "position": "D", "rating": "6.8", "captain": false, "substitute": false}, "offsides": null, "shots": {"total": 0, "on": 0}, "goals": {"total": null, "conceded": null, "assists": null, "saves": null}, "passes": {"total": 15, "key": 0, "accuracy": "65%"}, "tackles": {"total": 3, "blocks": 2, "interceptions": 1}, "duels": {"total": 12, "won": 6}, "dribbles": {"attempts": 0, "success": 0, "past": 1}, "fouls": {"drawn": 1, "committed": 4}, "cards": {"yellow": 0, "red": 0}, "penalty": {"won": null, "commited": null, "scored": 0, "missed": 0, "saved": null}}]}, {"player": {"id": 47284, "name": "Ander Iturraspe", "photo": "https://media-3.api-sports.io/football/players/47284.png"}, "statistics": [{"games": {"minutes": 73, "number": 8, "position": "M", "rating": "7.5", "captain": true, "substitute": false}, "offsides": null, "shots": {"total": 0, "on": 0}, "goals": {"total": null, "conceded": null, "assists": null, "saves": null}, "passes": {"total": 32, "key": 3, "accuracy": "86%"}, "tackles": {"total": 2, "blocks": 0, "interceptions": 1}, "duels": {"total": 8, "won": 5}, "dribbles": {"attempts": 0, "success": 0, "past": null}, "fouls": {"drawn": 1, "committed": 1}, "cards": {"yellow": 0, "red": 0}, "penalty": {"won": null, "commited": null, "scored": 0, "missed": 0, "saved": null}}]}, {"player": {"id": 47288, "name": "Mikel San José", "photo": "https://media-3.api-sports.io/football/players/47288.png"}, "statistics": [{"games": {"minutes": 90, "number": 6, "position": "M", "rating": "6.5", "captain": false, "substitute": false}, "offsides": null, "shots": {"total": 0, "on": 0}, "goals": {"total": null, "conceded": null, "assists": null, "saves": null}, "passes": {"total": 30, "key": 1, "accuracy": "73%"}, "tackles": {"total": 2, "blocks": 1, "interceptions": 0}, "duels": {"total": 13, "won": 8}, "dribbles": {"attempts": 1, "success": 1, "past": 1}, "fouls": {"drawn": 2, "committed": 2}, "cards": {"yellow": 0, "red": 0}, "penalty": {"won": null, "commited": null, "scored": 0, "missed": 0, "saved": null}}]}, {"player": {"id": 47276, "name": "Íñigo Lekue", "photo": "https://media-2.api-sports.io/football/players/47276.png"}, "statistics": [{"games": {"minutes": 50, "number": 15, "position": "D", "rating": "7.1", "captain": false, "substitute": false}, "offsides": null, "shots": {"total": 0, "on": 0}, "goals": {"total": null, "conceded": null, "assists": null, "saves": null}, "passes": {"total": 15, "key": 1, "accuracy": "75%"}, "tackles": {"total": 2, "blocks": 0, "interceptions": 1}, "duels": {"total": 7, "won": 6}, "dribbles": {"attempts": 1, "success": 0, "past": null}, "fouls": {"drawn": 1, "committed": 0}, "cards": {"yellow": 0, "red": 0}, "penalty": {"won": null, "commited": null, "scored": 0, "missed": 0, "saved": null}}]}, {"player": {"id": 47282, "name": "Raúl García", "photo": "https://media-2.api-sports.io/football/players/47282.png"}, "statistics": [{"games": {"minutes": 90, "number": 22, "position": "M", "rating": "7.0", "captain": false, "substitute": false}, "offsides": null, "shots": {"total": 4, "on": 3}, "goals": {"total": 1, "conceded": null, "assists": null, "saves": null}, "passes": {"total": 8, "key": 0, "accuracy": "40%"}, "tackles": {"total": 1, "blocks": 0, "interceptions": 4}, "duels": {"total": 13, "won": 7}, "dribbles": {"attempts": 0, "success": 0, "past": 2}, "fouls": {"drawn": 0, "committed": 4}, "cards": {"yellow": 1, "red": 0}, "penalty": {"won": null, "commited": null, "scored": 1, "missed": 0, "saved": null}}]}, {"player": {"id": 47279, "name": "Íñigo Córdoba", "photo": "https://media-1.api-sports.io/football/players/47279.png"}, "statistics": [{"games": {"minutes": 68, "number": 28, "position": "M", "rating": "6.8", "captain": false, "substitute": false}, "offsides": null, "shots": {"total": 0, "on": 0}, "goals": {"total": null, "conceded": null, "assists": null, "saves": null}, "passes": {"total": 10, "key": 0, "accuracy": "76%"}, "tackles": {"total": 3, "blocks": 0, "interceptions": 0}, "duels": {"total": 15, "won": 9}, "dribbles": {"attempts": 5, "success": 4, "past": 1}, "fouls": {"drawn": 1, "committed": 1}, "cards": {"yellow": 0, "red": 0}, "penalty": {"won": null, "commited": null, "scored": 0, "missed": 0, "saved": null}}]}, {"player": {"id": 47294, "name": "Iñaki Williams", "photo": "https://media-1.api-sports.io/football/players/47294.png"}, "statistics": [{"games": {"minutes": 90, "number": 11, "position": "F", "rating": "6.7", "captain": false, "substitute": false}, "offsides": null, "shots": {"total": 2, "on": 0}, "goals": {"total": null, "conceded": null, "assists": null, "saves": null}, "passes": {"total": 15, "key": 0, "accuracy": "75%"}, "tackles": {"total": null, "blocks": 0, "interceptions": 0}, "duels": {"total": 15, "won": 6}, "dribbles": {"attempts": 5, "success": 3, "past": null}, "fouls": {"drawn": 1, "committed": 1}, "cards": {"yellow": 1, "red": 0}, "penalty": {"won": null, "commited": null, "scored": 0, "missed": 0, "saved": null}}]}, {"player": {"id": 47289, "name": "Markel Susaeta", "photo": "https://media-3.api-sports.io/football/players/47289.png"}, "statistics": [{"games": {"minutes": 40, "number": 14, "position": "M", "rating": "6.8", "captain": false, "substitute": false}, "offsides": null, "shots": {"total": 0, "on": 0}, "goals": {"total": null, "conceded": null, "assists": null, "saves": null}, "passes": {"total": 19, "key": 2, "accuracy": "82%"}, "tackles": {"total": null, "blocks": 0, "interceptions": 0}, "duels": {"total": 3, "won": 2}, "dribbles": {"attempts": 1, "success": 0, "past": null}, "fouls": {"drawn": 1, "committed": 0}, "cards": {"yellow": 1, "red": 0}, "penalty": {"won": null, "commited": null, "scored": 0, "missed": 0, "saved": null}}]}, {"player": {"id": 47287, "name": "Mikel Rico", "photo": "https://media-1.api-sports.io/football/players/47287.png"}, "statistics": [{"games": {"minutes": 17, "number": 17, "position": "M", "rating": "6.6", "captain": false, "substitute": false}, "offsides": null, "shots": {"total": 0, "on": 0}, "goals": {"total": null, "conceded": null, "assists": null, "saves": null}, "passes": {"total": 6, "key": 0, "accuracy": "66%"}, "tackles": {"total": null, "blocks": 0, "interceptions": 0}, "duels": {"total": 3, "won": 2}, "dribbles": {"attempts": 0, "success": 0, "past": null}, "fouls": {"drawn": 2, "committed": 1}, "cards": {"yellow": 0, "red": 0}, "penalty": {"won": null, "commited": null, "scored": 0, "missed": 0, "saved": null}}]}, {"player": {"id": 2672, "name": "Iker Muniain", "photo": "https://media-2.api-sports.io/football/players/2672.png"}, "statistics": [{"games": {"minutes": 22, "number": 10, "position": "F", "rating": "6.3", "captain": false, "substitute": false}, "offsides": null, "shots": {"total": 0, "on": 0}, "goals": {"total": null, "conceded": null, "assists": null, "saves": null}, "passes": {"total": 9, "key": 0, "accuracy": "75%"}, "tackles": {"total": null, "blocks": 0, "interceptions": 0}, "duels": {"total": 4, "won": 1}, "dribbles": {"attempts": 0, "success": 0, "past": 1}, "fouls": {"drawn": 1, "committed": 1}, "cards": {"yellow": 1, "red": 0}, "penalty": {"won": null, "commited": null, "scored": 0, "missed": 0, "saved": null}}]}]}]}]}